Workbook

Sheet Comparison
A1: ΣΥΓΚΡΙΣΗ ΜΕ ΒΙΒΛΙΟΓΡΑΦΙΑ | ΣΥΜΠΛΗΡΩΜΕΝΟΣ ΠΙΝΑΚΑΣ
A2: 36 υπάρχοντα outputs · α=0,25 baseline · α=0,20/0,30 · χωρίς νέα προσομοίωση ή εξωτερική επικύρωση.
A5: Μελέτη | B5: Επαληθευμένο δημοσιευμένο εύρημα | C5: Δικά μας νέα αποτελέσματα | D5: Ερμηνεία και όριο συγκρισιμότητας | E5: Πρωτογενής πηγή
A6: Long et al. (2018) | B6: Περίπου 30% μείωση κοινοτικού ενεργειακού κόστους έναντι P2G και 12,4% μέση μείωση λογαριασμών καταναλωτών στο συγκεκριμένο παράδειγμα, με μηχανισμό αντιστάθμισης. | C6: Νέο baseline α=0,25: P2P έσοδα 425,80–805,29 €/έτος έναντι 1.049,45–1.586,40 € από αποτίμηση των ίδιων εξαγωγών στη spot. Η ανά περίπτωση υστέρηση εσόδων του πωλητή είναι 569,37–1.069,03 €. Παραμένει θετική και στις 36 περιπτώσεις: 559,75–1.069,03 €. | D6: Εναλλακτική αποτίμηση του ΙΔΙΟΥ dispatch, όχι νέα σύγκριση λειτουργίας P2P–P2G σε κοινότητα. Η μείωση πληρωμής για υποθετικό αγοραστή της ίδιας ποσότητας ισούται με την απώλεια εσόδου του πωλητή. Δεν είναι νέα κοινωνική ευημερία ούτε αποδεδειγμένο όφελος και των δύο. | E6: https://orca.cardiff.ac.uk/id/eprint/111870/7/1-s2.0-S0306261918308146-main.pdf
A7: Wang et al. (2025) | B7: Οι ετήσιες εισαγωγές τριών καταναλωτών αυξάνονται από 6.647 σε 7.510 kWh με προσθήκη μπαταρίας 5 kWh στο P2P. Προηγείται η φόρτιση, ενώ η αποθηκευμένη ενέργεια χρησιμοποιείται από τον prosumer. | C7: Για α=0,25 και αύξηση 10→30 kWh, εξαγωγές/proxy έγχυσης: A 12.641,75→12.630,99 kWh, B 14.031,31→14.005,91 kWh, C 12.475,73→13.148,40 kWh. Η κατεύθυνση της μεταβολής μεταξύ των δύο άκρων διατηρείται και στα άλλα α. Η B δεν είναι μονοτονική σε όλες τις ενδιάμεσες χωρητικότητες. | D7: Συγκρίνουμε τη σχέση λειτουργικού κανόνα–κατανομής ενέργειας, όχι ισοδύναμα νοικοκυριά. AF/AN = εξαγωγές/proxy διαθέσιμης έγχυσης, όχι παρατηρημένη ζήτηση αγοραστών. Οι B/C επιτρέπουν grid charging και battery exports. | E7: https://doi.org/10.1016/j.renene.2025.123494
A8: Quartierstrom – Ableitner et al. (2020) | B8: Στην περίοδο πεδίου: 58% της παραγωγής αξιοποιήθηκε στην κοινότητα και 33% της κατανάλωσης καλύφθηκε από τοπική παραγωγή. 35 νοικοκυριά και δύο εμπορικοί συμμετέχοντες. | C8: Ετήσια PV παραγωγή 15.486,00 kWh και φορτίο αναφοράς 4.244,32 kWh. Στο α=0,25: άμεση χρήση PV 1.872,05 kWh στις A/B και 2.205,61 στη C. Αντιστοιχεί στο 12,09%/14,24% της παραγωγής και στο 44,11%/51,97% του οικιακού φορτίου. | D8: Πρόκειται για ΑΜΕΣΗ χρήση PV από ένα νοικοκυριό, όχι συνολική κοινοτική αυτοκατανάλωση/αυτάρκεια. Δεν προσμετράμε ως ταυτόσημα μεγέθη τοπικές συναλλαγές ή ενέργεια μπαταρίας χωρίς ιχνηλάτηση προέλευσης. | E8: https://doi.org/10.1016/j.apenergy.2020.115061
A9: LAMP – Staudt & Richter (2025) | B9: Η μέση προσφορά αγοράς για τοπική PV ενέργεια μειώνεται από 25,1 σε 20,1 λεπτά €/kWh έως τον Σεπτέμβριο 2020. Συμμετέχουν 11 νοικοκυριά χωρίς οικιακές μπαταρίες. | C9: Οι 36 περιπτώσεις μας μεταβάλλουν α και το ω που προκύπτει από τον ίδιο κανόνα βαθμονόμησης. Δεν εκτιμούν πραγματικές προσφορές. Διατηρούνται οι αρνητικές εκβάσεις και δεν επιβάλλονται περιορισμοί συμμετοχής του buyer. | D9: Οι προσφορές δεν είναι εκτιμήσεις ω ούτε utility-indifference prices. Εμπειρικό πλαίσιο για τα όρια των παραδοχών προτιμήσεων, όχι validation των α/ω, των στρατηγικών μπαταρίας ή της τιμής εκκαθάρισης. | E9: https://link.springer.com/article/10.1186/s13705-025-00511-5
A12: Ολοκληρωμένη σύγκριση δημοσιευμένων ευρημάτων — όχι νέα εκτέλεση μοντέλου ή εξωτερική επικύρωση.
A14: Χρήση: ο πίνακας στο τέλος των Results. Η ερμηνεία στο Discussion και τα όρια στη Limitations and Future Scope. Baseline_025: 12 βασικές διαμορφώσεις. Energy_36 / Cashflows_36: όλοι οι αριθμοί και οι τύποι. Alpha_Ranges / Capacity_Check: έλεγχος των συγκεκριμένων τάσεων. Original_Table: αυτούσιο το αρχικό περιεχόμενο.

Sheet Source_Totals
A1: SOURCE TOTALS | 36 STORED OUTPUTS
A2: Imported cached values from Summary and Parameters. No solver calls. Files and SHA-256 hashes at right; source-cell mapping in Definitions.
A5: Case | B5: Alpha (€/kWh²) | C5: Strategy | D5: Capacity (kWh) | E5: PV (kWh) | F5: Base demand (kWh) | G5: Direct PV use (kWh) | H5: Charge (kWh) | I5: Discharge (kWh) | J5: Grid to load (kWh) | K5: Exports / injection proxy (kWh) | L5: All grid imports (kWh) | M5: AI utility (EUR) | N5: AO utility reported (EUR) | O5: BT utility net of grid cost (EUR) | P5: P2P receipts (EUR) | Q5: Spot operating cost (EUR) | R5: Storage saving proxy (EUR) | S5: Battery losses (kWh) | T5: Final–initial SOC (kWh) | U5: Active P2P hours | V5: Wear coefficient (€/kWh) | W5: Mean omega (€/kWh) | X5: Monthly–annual max residual | Y5: XLSX SHA-256 | Z5: ZIP archive | AA5: Member path | AB5: Buyer utility reported (EUR) | AC5: SW_P2P reported (EUR)
A6: a0.20_A_10kWh | B6: 0.2 | C6: A | D6: 10 | E6: 15485.996 | F6: 4244.3164 | G6: 1798.7407 | H6: 1042.8352 | I6: 881.46446 | J6: 1564.1112 | K6: 12644.42 | L6: 1564.1112 | M6: 1499.137 | N6: 1089.6649 | O6: 917.19938 | P6: 478.32015 | Q6: -830.06327 | R6: 38.783501 | S6: 161.37558 | T6: -0.0048236279 | U6: 3359 | V6: 0.03 | W6: 0.20096169 | X6: 1.8189894e-12 | Y6: fdb68aaa8af8379bff3171c3a718b326eb48520077b076cf202c0358d2931aaf | Z6: Alpha_0.20_12_Excel_Outputs.zip | AA6: Alpha_0.20/Alpha_0.20_Strategy_A_Battery_10kWh.xlsx | AB6: -4154.6678 | AC6: -5682.2063
A7: a0.20_A_15kWh | B7: 0.2 | C7: A | D7: 15 | E7: 15485.996 | F7: 4244.3164 | G7: 1798.7407 | H7: 1049.1136 | I7: 885.59838 | J7: 1559.9773 | K7: 12638.142 | L7: 1559.9773 | M7: 1498.881 | N7: 1088.8108 | O7: 916.97404 | P7: 477.77843 | Q7: -829.80729 | R7: 38.527519 | S7: 163.02082 | T7: 0.49436644 | U7: 3357 | V7: 0.03 | W7: 0.20096169 | X7: 9.094947e-13 | Y7: d2e2f1a386a2ad62e01772be76ea1d4cf0be8e182927609f2654a5d6b6020fd4 | Z7: Alpha_0.20_12_Excel_Outputs.zip | AA7: Alpha_0.20/Alpha_0.20_Strategy_A_Battery_15kWh.xlsx | AB7: -4153.6438 | AC7: -5680.8948
A8: a0.20_A_20kWh | B8: 0.2 | C8: A | D8: 20 | E8: 15485.996 | F8: 4244.3164 | G8: 1798.7407 | H8: 1051.3508 | I8: 886.30843 | J8: 1559.2673 | K8: 12635.905 | L8: 1559.2673 | M8: 1498.7466 | N8: 1088.5829 | O8: 916.85126 | P8: 477.63896 | Q8: -829.67285 | R8: 38.393079 | S8: 164.04884 | T8: 0.9935565 | U8: 3356 | V8: 0.03 | W8: 0.20096169 | X8: 9.094947e-13 | Y8: b7d4dd0dd8c9409f4846a4717bfaf114b041ea2456c7d44d9d468d58636bb7e6 | Z8: Alpha_0.20_12_Excel_Outputs.zip | AA8: Alpha_0.20/Alpha_0.20_Strategy_A_Battery_20kWh.xlsx | AB8: -4153.0845 | AC8: -5680.1499
A9: a0.20_A_30kWh | B9: 0.2 | C9: A | D9: 30 | E9: 15485.996 | F9: 4244.3164 | G9: 1798.7407 | H9: 1054.1493 | I9: 886.30843 | J9: 1559.2673 | K9: 12633.106 | L9: 1559.2673 | M9: 1498.5204 | N9: 1088.4041 | O9: 916.67245 | P9: 477.5441 | Q9: -829.44665 | R9: 38.166885 | S9: 165.8489 | T9: 1.9919366 | U9: 3356 | V9: 0.03 | W9: 0.20096169 | X9: 9.094947e-13 | Y9: e1ca5c79db317dd60ce1963853cc29d38512178ccec50f80156ef4076adb786b | Z9: Alpha_0.20_12_Excel_Outputs.zip | AA9: Alpha_0.20/Alpha_0.20_Strategy_A_Battery_30kWh.xlsx | AB9: -4152.3385 | AC9: -5679.0776
A10: a0.20_B_10kWh | B10: 0.2 | C10: B | D10: 10 | E10: 15485.996 | F10: 4244.3164 | G10: 1798.7407 | H10: 2905.8909 | I10: 2466.0978 | J10: 2032.1835 | K10: 14058.374 | L10: 3256.4872 | M10: 1576.5775 | N10: 1273.8922 | O10: 942.07551 | P10: 765.97812 | Q10: -907.50373 | R10: 116.22396 | S10: 447.79305 | T10: -8 | U10: 3549 | V10: 0.03 | W10: 0.20096169 | X10: 9.094947e-13 | Y10: aa161bcf0e641f499e8f37f0efafc1a1a18d74863f2226880707f82c76e48b81 | Z10: Alpha_0.20_12_Excel_Outputs.zip | AA10: Alpha_0.20/Alpha_0.20_Strategy_B_Battery_10kWh.xlsx | AB10: -5164.3285 | AC10: -6677.9061
A11: a0.20_B_15kWh | B11: 0.2 | C11: B | D11: 15 | E11: 15485.996 | F11: 4244.3164 | G11: 1798.7407 | H11: 3793.6506 | I11: 3220.745 | J11: 1952.3973 | K11: 14048.562 | L11: 3379.7879 | M11: 1611.6718 | N11: 1229.276 | O11: 892.87988 | P11: 770.63407 | Q11: -942.59809 | R11: 151.31832 | S11: 584.90554 | T11: -12 | U11: 3603 | V11: 0.03 | W11: 0.20096169 | X11: 9.094947e-13 | Y11: 8f9afbf9b7e0f474fc4fc60b68257e2f074c0ccd9bade85ec04c3bfc0a767c3e | Z11: Alpha_0.20_12_Excel_Outputs.zip | AA11: Alpha_0.20/Alpha_0.20_Strategy_B_Battery_15kWh.xlsx | AB11: -4937.906 | AC11: -6421.1746
A12: a0.20_B_20kWh | B12: 0.2 | C12: B | D12: 20 | E12: 15485.996 | F12: 4244.3164 | G12: 1798.7407 | H12: 4400.1881 | I12: 3736.6595 | J12: 1874.7242 | K12: 14009.28 | L12: 3431.1288 | M12: 1624.6128 | N12: 1214.8524 | O12: 876.49982 | P12: 789.88404 | Q12: -955.53906 | R12: 164.2593 | S12: 678.78978 | T12: -15.26119 | U12: 3761 | V12: 0.03 | W12: 0.20096169 | X12: 4.5474735e-13 | Y12: 3988f57cde4731842e1dc0cba35083aa416e4eb38452841cbed3097d1b40300e | Z12: Alpha_0.20_12_Excel_Outputs.zip | AA12: Alpha_0.20/Alpha_0.20_Strategy_B_Battery_20kWh.xlsx | AB12: -4664.5588 | AC12: -6089.872
A13: a0.20_B_30kWh | B13: 0.2 | C13: B | D13: 30 | E13: 15485.996 | F13: 4244.3164 | G13: 1798.7407 | H13: 4969.1296 | I13: 4222.7651 | J13: 1838.4999 | K13: 14026.101 | L13: 3530.7852 | M13: 1626.2747 | N13: 1201.5865 | O13: 854.00832 | P13: 808.26956 | Q13: -957.20096 | R13: 165.92119 | S13: 767.62558 | T13: -21.26111 | U13: 3814 | V13: 0.03 | W13: 0.20096169 | X13: 2.2737368e-13 | Y13: 687e9fa203f40f49da6eb50c271329da863ff46518a1426c268761f4bf7d87ba | Z13: Alpha_0.20_12_Excel_Outputs.zip | AA13: Alpha_0.20/Alpha_0.20_Strategy_B_Battery_30kWh.xlsx | AB13: -4435.358 | AC13: -5814.7704
A14: a0.20_C_10kWh | B14: 0.2 | C14: C | D14: 10 | E14: 15485.996 | F14: 4244.3164 | G14: 2205.612 | H14: 3174.7969 | I14: 2686.4706 | J14: 1401.7179 | K14: 12475.726 | L14: 1722.3726 | M14: 1655.2893 | N14: 919.03318 | O14: 756.97981 | P14: 425.79744 | Q14: -986.21551 | R14: 194.93574 | S14: 488.32628 | T14: 0 | U14: 3918 | V14: 0.03 | W14: 0.20096169 | X14: 1.8189894e-12 | Y14: 2fc400957dee09282d7847c65c6c6fb0cc7057ce5f1fd0c83e5779a574d6361a | Z14: Alpha_0.20_12_Excel_Outputs.zip | AA14: Alpha_0.20/Alpha_0.20_Strategy_C_Battery_10kWh.xlsx | AB14: -3453.1004 | AC14: -4941.036
A15: a0.20_C_15kWh | B15: 0.2 | C15: C | D15: 15 | E15: 15485.996 | F15: 4244.3164 | G15: 2205.612 | H15: 4334.0686 | I15: 3667.291 | J15: 1362.9558 | K15: 12513.658 | L15: 1938.7559 | M15: 1707.3932 | N15: 888.35909 | O15: 724.89388 | P15: 459.32611 | Q15: -1038.3194 | R15: 247.03965 | S15: 666.77765 | T15: 0 | U15: 3813 | V15: 0.03 | W15: 0.20096169 | X15: 1.8189894e-12 | Y15: 4547223c5d301a629be5d242bac6595d11f246de239cf7fd040c9e37249d1d2f | Z15: Alpha_0.20_12_Excel_Outputs.zip | AA15: Alpha_0.20/Alpha_0.20_Strategy_C_Battery_15kWh.xlsx | AB15: -3404.8564 | AC15: -4858.4758
A16: a0.20_C_20kWh | B16: 0.2 | C16: C | D16: 20 | E16: 15485.996 | F16: 4244.3164 | G16: 2205.612 | H16: 5142.7785 | I16: 4351.3085 | J16: 1347.5186 | K16: 12778.659 | L16: 2328.4494 | M16: 1737.4526 | N16: 876.43909 | O16: 704.20063 | P16: 492.18794 | Q16: -1068.3788 | R16: 277.09906 | S16: 791.47003 | T16: 0 | U16: 3907 | V16: 0.03 | W16: 0.20096169 | X16: 9.094947e-13 | Y16: 9f58087ea8dd46abef15347264067613a67461106b1824eb8fb07111c2f0c15a | Z16: Alpha_0.20_12_Excel_Outputs.zip | AA16: Alpha_0.20/Alpha_0.20_Strategy_C_Battery_20kWh.xlsx | AB16: -3430.1713 | AC16: -4884.5123
A17: a0.20_C_30kWh | B17: 0.2 | C17: C | D17: 30 | E17: 15485.996 | F17: 4244.3164 | G17: 2205.612 | H17: 5717.5564 | I17: 4836.5801 | J17: 1343.0334 | K17: 13148.397 | L17: 2787.6931 | M17: 1757.0731 | N17: 869.82312 | O17: 688.04527 | P17: 517.37345 | Q17: -1087.9994 | R17: 296.71962 | S17: 880.97631 | T17: 0 | U17: 3869 | V17: 0.03 | W17: 0.20096169 | X17: 9.094947e-13 | Y17: aaae8d8751498eae5d18b4bf889625ab4dafd763fbf3892623d42c3908f9f528 | Z17: Alpha_0.20_12_Excel_Outputs.zip | AA17: Alpha_0.20/Alpha_0.20_Strategy_C_Battery_30kWh.xlsx | AB17: -3648.785 | AC17: -5148.3239
... A41: a0.30_C_30kWh | B41: 0.3 | C41: C | D41: 30 | E41: 15485.996 | F41: 4244.3164 | G41: 2205.612 | H41: 5717.5564 | I41: 4836.5801 | J41: 1343.0334 | K41: 13148.397 | L41: 2787.6931 | M41: 1870.95 | N41: 983.69995 | O41: 801.92211 | P41: 517.37345 | Q41: -1087.9994 | R41: 296.71962 | S41: 880.97631 | T41: 0 | U41: 3869 | V41: 0.03 | W41: 0.24941279 | X41: 9.094947e-13 | Y41: 40595a4510460a67b174ebb7229a4d65c6ca22dc7f346e042d06a09fd966da9d | Z41: Alpha_0.30_12_Excel_Outputs.zip | AA41: Alpha_0.30/Alpha_0.30_Strategy_C_Battery_30kWh.xlsx | AB41: -6002.9247 | AC41: -7502.4636

Sheet Energy_36
A1: ENERGY | KEEP PARTICIPANT BOUNDARIES EXPLICIT
A2: X is grid-to-load for the modelled prosumer. AG includes grid charging. AF = AN is an export/injection proxy, not matched buyer demand.
A5: Case | B5: α (€/kWh²) | C5: Strategy | D5: Battery (kWh) | E5: PV (kWh) | F5: Demand (kWh) | G5: Direct PV use (kWh) | H5: Grid→load (kWh) | I5: All grid imports (kWh) | J5: Grid→battery (kWh) | K5: Exports / injection proxy (kWh) | L5: Charge (kWh) | M5: Discharge (kWh) | N5: Battery→load (kWh) | O5: Battery→export (kWh) | P5: Direct PV / generation (%) | Q5: Direct PV / load (%) | R5: Final–initial SOC (kWh)
A6: =Source_Totals!A6 -> a0.20_A_10kWh | B6: =Source_Totals!B6 -> 0.2 | C6: =Source_Totals!C6 -> A | D6: =Source_Totals!D6 -> 10 | E6: =Source_Totals!E6 -> 15485.996 | F6: =Source_Totals!F6 -> 4244.3164 | G6: =Source_Totals!G6 -> 1798.7407 | H6: =Source_Totals!J6 -> 1564.1112 | I6: =Source_Totals!L6 -> 1564.1112 | J6: =I6-H6 -> 0 | K6: =Source_Totals!K6 -> 12644.42 | L6: =Source_Totals!H6 -> 1042.8352 | M6: =Source_Totals!I6 -> 881.46446 | N6: =F6-G6-H6 -> 881.46446 | O6: =M6-N6 -> 0 | P6: =G6/E6 -> 0.11615273 | Q6: =G6/F6 -> 0.42379986 | R6: =Source_Totals!T6 -> -0.0048236279
A7: =Source_Totals!A7 -> a0.20_A_15kWh | B7: =Source_Totals!B7 -> 0.2 | C7: =Source_Totals!C7 -> A | D7: =Source_Totals!D7 -> 15 | E7: =Source_Totals!E7 -> 15485.996 | F7: =Source_Totals!F7 -> 4244.3164 | G7: =Source_Totals!G7 -> 1798.7407 | H7: =Source_Totals!J7 -> 1559.9773 | I7: =Source_Totals!L7 -> 1559.9773 | J7: =I7-H7 -> 0 | K7: =Source_Totals!K7 -> 12638.142 | L7: =Source_Totals!H7 -> 1049.1136 | M7: =Source_Totals!I7 -> 885.59838 | N7: =F7-G7-H7 -> 885.59838 | O7: =M7-N7 -> 0 | P7: =G7/E7 -> 0.11615273 | Q7: =G7/F7 -> 0.42379986 | R7: =Source_Totals!T7 -> 0.49436644
A8: =Source_Totals!A8 -> a0.20_A_20kWh | B8: =Source_Totals!B8 -> 0.2 | C8: =Source_Totals!C8 -> A | D8: =Source_Totals!D8 -> 20 | E8: =Source_Totals!E8 -> 15485.996 | F8: =Source_Totals!F8 -> 4244.3164 | G8: =Source_Totals!G8 -> 1798.7407 | H8: =Source_Totals!J8 -> 1559.2673 | I8: =Source_Totals!L8 -> 1559.2673 | J8: =I8-H8 -> 0 | K8: =Source_Totals!K8 -> 12635.905 | L8: =Source_Totals!H8 -> 1051.3508 | M8: =Source_Totals!I8 -> 886.30843 | N8: =F8-G8-H8 -> 886.30843 | O8: =M8-N8 -> 0 | P8: =G8/E8 -> 0.11615273 | Q8: =G8/F8 -> 0.42379986 | R8: =Source_Totals!T8 -> 0.9935565
A9: =Source_Totals!A9 -> a0.20_A_30kWh | B9: =Source_Totals!B9 -> 0.2 | C9: =Source_Totals!C9 -> A | D9: =Source_Totals!D9 -> 30 | E9: =Source_Totals!E9 -> 15485.996 | F9: =Source_Totals!F9 -> 4244.3164 | G9: =Source_Totals!G9 -> 1798.7407 | H9: =Source_Totals!J9 -> 1559.2673 | I9: =Source_Totals!L9 -> 1559.2673 | J9: =I9-H9 -> 0 | K9: =Source_Totals!K9 -> 12633.106 | L9: =Source_Totals!H9 -> 1054.1493 | M9: =Source_Totals!I9 -> 886.30843 | N9: =F9-G9-H9 -> 886.30843 | O9: =M9-N9 -> 0 | P9: =G9/E9 -> 0.11615273 | Q9: =G9/F9 -> 0.42379986 | R9: =Source_Totals!T9 -> 1.9919366
A10: =Source_Totals!A10 -> a0.20_B_10kWh | B10: =Source_Totals!B10 -> 0.2 | C10: =Source_Totals!C10 -> B | D10: =Source_Totals!D10 -> 10 | E10: =Source_Totals!E10 -> 15485.996 | F10: =Source_Totals!F10 -> 4244.3164 | G10: =Source_Totals!G10 -> 1798.7407 | H10: =Source_Totals!J10 -> 2032.1835 | I10: =Source_Totals!L10 -> 3256.4872 | J10: =I10-H10 -> 1224.3038 | K10: =Source_Totals!K10 -> 14058.374 | L10: =Source_Totals!H10 -> 2905.8909 | M10: =Source_Totals!I10 -> 2466.0978 | N10: =F10-G10-H10 -> 413.39225 | O10: =M10-N10 -> 2052.7056 | P10: =G10/E10 -> 0.11615273 | Q10: =G10/F10 -> 0.42379986 | R10: =Source_Totals!T10 -> -8
A11: =Source_Totals!A11 -> a0.20_B_15kWh | B11: =Source_Totals!B11 -> 0.2 | C11: =Source_Totals!C11 -> B | D11: =Source_Totals!D11 -> 15 | E11: =Source_Totals!E11 -> 15485.996 | F11: =Source_Totals!F11 -> 4244.3164 | G11: =Source_Totals!G11 -> 1798.7407 | H11: =Source_Totals!J11 -> 1952.3973 | I11: =Source_Totals!L11 -> 3379.7879 | J11: =I11-H11 -> 1427.3907 | K11: =Source_Totals!K11 -> 14048.562 | L11: =Source_Totals!H11 -> 3793.6506 | M11: =Source_Totals!I11 -> 3220.745 | N11: =F11-G11-H11 -> 493.17843 | O11: =M11-N11 -> 2727.5666 | P11: =G11/E11 -> 0.11615273 | Q11: =G11/F11 -> 0.42379986 | R11: =Source_Totals!T11 -> -12
A12: =Source_Totals!A12 -> a0.20_B_20kWh | B12: =Source_Totals!B12 -> 0.2 | C12: =Source_Totals!C12 -> B | D12: =Source_Totals!D12 -> 20 | E12: =Source_Totals!E12 -> 15485.996 | F12: =Source_Totals!F12 -> 4244.3164 | G12: =Source_Totals!G12 -> 1798.7407 | H12: =Source_Totals!J12 -> 1874.7242 | I12: =Source_Totals!L12 -> 3431.1288 | J12: =I12-H12 -> 1556.4046 | K12: =Source_Totals!K12 -> 14009.28 | L12: =Source_Totals!H12 -> 4400.1881 | M12: =Source_Totals!I12 -> 3736.6595 | N12: =F12-G12-H12 -> 570.85151 | O12: =M12-N12 -> 3165.808 | P12: =G12/E12 -> 0.11615273 | Q12: =G12/F12 -> 0.42379986 | R12: =Source_Totals!T12 -> -15.26119
A13: =Source_Totals!A13 -> a0.20_B_30kWh | B13: =Source_Totals!B13 -> 0.2 | C13: =Source_Totals!C13 -> B | D13: =Source_Totals!D13 -> 30 | E13: =Source_Totals!E13 -> 15485.996 | F13: =Source_Totals!F13 -> 4244.3164 | G13: =Source_Totals!G13 -> 1798.7407 | H13: =Source_Totals!J13 -> 1838.4999 | I13: =Source_Totals!L13 -> 3530.7852 | J13: =I13-H13 -> 1692.2853 | K13: =Source_Totals!K13 -> 14026.101 | L13: =Source_Totals!H13 -> 4969.1296 | M13: =Source_Totals!I13 -> 4222.7651 | N13: =F13-G13-H13 -> 607.0758 | O13: =M13-N13 -> 3615.6893 | P13: =G13/E13 -> 0.11615273 | Q13: =G13/F13 -> 0.42379986 | R13: =Source_Totals!T13 -> -21.26111
A14: =Source_Totals!A14 -> a0.20_C_10kWh | B14: =Source_Totals!B14 -> 0.2 | C14: =Source_Totals!C14 -> C | D14: =Source_Totals!D14 -> 10 | E14: =Source_Totals!E14 -> 15485.996 | F14: =Source_Totals!F14 -> 4244.3164 | G14: =Source_Totals!G14 -> 2205.612 | H14: =Source_Totals!J14 -> 1401.7179 | I14: =Source_Totals!L14 -> 1722.3726 | J14: =I14-H14 -> 320.65474 | K14: =Source_Totals!K14 -> 12475.726 | L14: =Source_Totals!H14 -> 3174.7969 | M14: =Source_Totals!I14 -> 2686.4706 | N14: =F14-G14-H14 -> 636.98645 | O14: =M14-N14 -> 2049.4841 | P14: =G14/E14 -> 0.14242623 | Q14: =G14/F14 -> 0.51966249 | R14: =Source_Totals!T14 -> 0
A15: =Source_Totals!A15 -> a0.20_C_15kWh | B15: =Source_Totals!B15 -> 0.2 | C15: =Source_Totals!C15 -> C | D15: =Source_Totals!D15 -> 15 | E15: =Source_Totals!E15 -> 15485.996 | F15: =Source_Totals!F15 -> 4244.3164 | G15: =Source_Totals!G15 -> 2205.612 | H15: =Source_Totals!J15 -> 1362.9558 | I15: =Source_Totals!L15 -> 1938.7559 | J15: =I15-H15 -> 575.80009 | K15: =Source_Totals!K15 -> 12513.658 | L15: =Source_Totals!H15 -> 4334.0686 | M15: =Source_Totals!I15 -> 3667.291 | N15: =F15-G15-H15 -> 675.74851 | O15: =M15-N15 -> 2991.5424 | P15: =G15/E15 -> 0.14242623 | Q15: =G15/F15 -> 0.51966249 | R15: =Source_Totals!T15 -> 0
A16: =Source_Totals!A16 -> a0.20_C_20kWh | B16: =Source_Totals!B16 -> 0.2 | C16: =Source_Totals!C16 -> C | D16: =Source_Totals!D16 -> 20 | E16: =Source_Totals!E16 -> 15485.996 | F16: =Source_Totals!F16 -> 4244.3164 | G16: =Source_Totals!G16 -> 2205.612 | H16: =Source_Totals!J16 -> 1347.5186 | I16: =Source_Totals!L16 -> 2328.4494 | J16: =I16-H16 -> 980.93083 | K16: =Source_Totals!K16 -> 12778.659 | L16: =Source_Totals!H16 -> 5142.7785 | M16: =Source_Totals!I16 -> 4351.3085 | N16: =F16-G16-H16 -> 691.18572 | O16: =M16-N16 -> 3660.1227 | P16: =G16/E16 -> 0.14242623 | Q16: =G16/F16 -> 0.51966249 | R16: =Source_Totals!T16 -> 0
A17: =Source_Totals!A17 -> a0.20_C_30kWh | B17: =Source_Totals!B17 -> 0.2 | C17: =Source_Totals!C17 -> C | D17: =Source_Totals!D17 -> 30 | E17: =Source_Totals!E17 -> 15485.996 | F17: =Source_Totals!F17 -> 4244.3164 | G17: =Source_Totals!G17 -> 2205.612 | H17: =Source_Totals!J17 -> 1343.0334 | I17: =Source_Totals!L17 -> 2787.6931 | J17: =I17-H17 -> 1444.6597 | K17: =Source_Totals!K17 -> 13148.397 | L17: =Source_Totals!H17 -> 5717.5564 | M17: =Source_Totals!I17 -> 4836.5801 | N17: =F17-G17-H17 -> 695.67095 | O17: =M17-N17 -> 4140.9092 | P17: =G17/E17 -> 0.14242623 | Q17: =G17/F17 -> 0.51966249 | R17: =Source_Totals!T17 -> 0
... A41: =Source_Totals!A41 -> a0.30_C_30kWh | B41: =Source_Totals!B41 -> 0.3 | C41: =Source_Totals!C41 -> C | D41: =Source_Totals!D41 -> 30 | E41: =Source_Totals!E41 -> 15485.996 | F41: =Source_Totals!F41 -> 4244.3164 | G41: =Source_Totals!G41 -> 2205.612 | H41: =Source_Totals!J41 -> 1343.0334 | I41: =Source_Totals!L41 -> 2787.6931 | J41: =I41-H41 -> 1444.6597 | K41: =Source_Totals!K41 -> 13148.397 | L41: =Source_Totals!H41 -> 5717.5564 | M41: =Source_Totals!I41 -> 4836.5801 | N41: =F41-G41-H41 -> 695.67095 | O41: =M41-N41 -> 4140.9092 | P41: =G41/E41 -> 0.14242623 | Q41: =G41/F41 -> 0.51966249 | R41: =Source_Totals!T41 -> 0

Sheet Cashflows_36
A1: CASH FLOWS | SAME-DISPATCH REVALUATION
A2: Import expenditure + throughput wear − alternative export receipts. Negative net cost = net inflow, not lifetime profit. No CAPEX, tax or network-fee comparison.
A5: Case | B5: α (€/kWh²) | C5: Strategy | D5: Battery (kWh) | E5: Import expenditure (€) | F5: Wear cost (€) | G5: Spot export receipts (€) | H5: P2P export receipts (€) | I5: Spot net operating cost (€) | J5: P2P same-dispatch net cost (€) | K5: Seller receipts: P2P − spot (€) | L5: Same-quantity buyer payment reduction (€) | M5: Transfer sum (€) | N5: Utility identity residual (€)
A6: =Source_Totals!A6 -> a0.20_A_10kWh | B6: =Source_Totals!B6 -> 0.2 | C6: =Source_Totals!C6 -> A | D6: =Source_Totals!D6 -> 10 | E6: =Source_Totals!N6-Source_Totals!O6 -> 172.46554 | F6: =Source_Totals!V6*(Source_Totals!H6+Source_Totals!I6) -> 57.72899 | G6: =E6+F6-Source_Totals!Q6 -> 1060.2578 | H6: =Source_Totals!P6 -> 478.32015 | I6: =E6+F6-G6 -> -830.06327 | J6: =E6+F6-H6 -> -248.12562 | K6: =H6-G6 -> -581.93765 | L6: =G6-H6 -> 581.93765 | M6: =K6+L6 -> 0 | N6: =Source_Totals!M6-Source_Totals!O6-L6 -> 0
A7: =Source_Totals!A7 -> a0.20_A_15kWh | B7: =Source_Totals!B7 -> 0.2 | C7: =Source_Totals!C7 -> A | D7: =Source_Totals!D7 -> 15 | E7: =Source_Totals!N7-Source_Totals!O7 -> 171.83679 | F7: =Source_Totals!V7*(Source_Totals!H7+Source_Totals!I7) -> 58.041358 | G7: =E7+F7-Source_Totals!Q7 -> 1059.6854 | H7: =Source_Totals!P7 -> 477.77843 | I7: =E7+F7-G7 -> -829.80729 | J7: =E7+F7-H7 -> -247.90028 | K7: =H7-G7 -> -581.907 | L7: =G7-H7 -> 581.907 | M7: =K7+L7 -> 0 | N7: =Source_Totals!M7-Source_Totals!O7-L7 -> 0
A8: =Source_Totals!A8 -> a0.20_A_20kWh | B8: =Source_Totals!B8 -> 0.2 | C8: =Source_Totals!C8 -> A | D8: =Source_Totals!D8 -> 20 | E8: =Source_Totals!N8-Source_Totals!O8 -> 171.73168 | F8: =Source_Totals!V8*(Source_Totals!H8+Source_Totals!I8) -> 58.129778 | G8: =E8+F8-Source_Totals!Q8 -> 1059.5343 | H8: =Source_Totals!P8 -> 477.63896 | I8: =E8+F8-G8 -> -829.67285 | J8: =E8+F8-H8 -> -247.7775 | K8: =H8-G8 -> -581.89534 | L8: =G8-H8 -> 581.89534 | M8: =K8+L8 -> 0 | N8: =Source_Totals!M8-Source_Totals!O8-L8 -> 0
A9: =Source_Totals!A9 -> a0.20_A_30kWh | B9: =Source_Totals!B9 -> 0.2 | C9: =Source_Totals!C9 -> A | D9: =Source_Totals!D9 -> 30 | E9: =Source_Totals!N9-Source_Totals!O9 -> 171.73168 | F9: =Source_Totals!V9*(Source_Totals!H9+Source_Totals!I9) -> 58.213731 | G9: =E9+F9-Source_Totals!Q9 -> 1059.3921 | H9: =Source_Totals!P9 -> 477.5441 | I9: =E9+F9-G9 -> -829.44665 | J9: =E9+F9-H9 -> -247.59869 | K9: =H9-G9 -> -581.84796 | L9: =G9-H9 -> 581.84796 | M9: =K9+L9 -> 0 | N9: =Source_Totals!M9-Source_Totals!O9-L9 -> 0
A10: =Source_Totals!A10 -> a0.20_B_10kWh | B10: =Source_Totals!B10 -> 0.2 | C10: =Source_Totals!C10 -> B | D10: =Source_Totals!D10 -> 10 | E10: =Source_Totals!N10-Source_Totals!O10 -> 331.81671 | F10: =Source_Totals!V10*(Source_Totals!H10+Source_Totals!I10) -> 161.15966 | G10: =E10+F10-Source_Totals!Q10 -> 1400.4801 | H10: =Source_Totals!P10 -> 765.97812 | I10: =E10+F10-G10 -> -907.50373 | J10: =E10+F10-H10 -> -273.00175 | K10: =H10-G10 -> -634.50198 | L10: =G10-H10 -> 634.50198 | M10: =K10+L10 -> 0 | N10: =Source_Totals!M10-Source_Totals!O10-L10 -> 0
A11: =Source_Totals!A11 -> a0.20_B_15kWh | B11: =Source_Totals!B11 -> 0.2 | C11: =Source_Totals!C11 -> B | D11: =Source_Totals!D11 -> 15 | E11: =Source_Totals!N11-Source_Totals!O11 -> 336.39609 | F11: =Source_Totals!V11*(Source_Totals!H11+Source_Totals!I11) -> 210.43187 | G11: =E11+F11-Source_Totals!Q11 -> 1489.426 | H11: =Source_Totals!P11 -> 770.63407 | I11: =E11+F11-G11 -> -942.59809 | J11: =E11+F11-H11 -> -223.80612 | K11: =H11-G11 -> -718.79197 | L11: =G11-H11 -> 718.79197 | M11: =K11+L11 -> 0 | N11: =Source_Totals!M11-Source_Totals!O11-L11 -> 0
A12: =Source_Totals!A12 -> a0.20_B_20kWh | B12: =Source_Totals!B12 -> 0.2 | C12: =Source_Totals!C12 -> B | D12: =Source_Totals!D12 -> 20 | E12: =Source_Totals!N12-Source_Totals!O12 -> 338.35255 | F12: =Source_Totals!V12*(Source_Totals!H12+Source_Totals!I12) -> 244.10543 | G12: =E12+F12-Source_Totals!Q12 -> 1537.997 | H12: =Source_Totals!P12 -> 789.88404 | I12: =E12+F12-G12 -> -955.53906 | J12: =E12+F12-H12 -> -207.42606 | K12: =H12-G12 -> -748.11301 | L12: =G12-H12 -> 748.11301 | M12: =K12+L12 -> 0 | N12: =Source_Totals!M12-Source_Totals!O12-L12 -> 0
A13: =Source_Totals!A13 -> a0.20_B_30kWh | B13: =Source_Totals!B13 -> 0.2 | C13: =Source_Totals!C13 -> B | D13: =Source_Totals!D13 -> 30 | E13: =Source_Totals!N13-Source_Totals!O13 -> 347.57816 | F13: =Source_Totals!V13*(Source_Totals!H13+Source_Totals!I13) -> 275.75684 | G13: =E13+F13-Source_Totals!Q13 -> 1580.536 | H13: =Source_Totals!P13 -> 808.26956 | I13: =E13+F13-G13 -> -957.20096 | J13: =E13+F13-H13 -> -184.93456 | K13: =H13-G13 -> -772.2664 | L13: =G13-H13 -> 772.2664 | M13: =K13+L13 -> 0 | N13: =Source_Totals!M13-Source_Totals!O13-L13 -> 0
A14: =Source_Totals!A14 -> a0.20_C_10kWh | B14: =Source_Totals!B14 -> 0.2 | C14: =Source_Totals!C14 -> C | D14: =Source_Totals!D14 -> 10 | E14: =Source_Totals!N14-Source_Totals!O14 -> 162.05337 | F14: =Source_Totals!V14*(Source_Totals!H14+Source_Totals!I14) -> 175.83802 | G14: =E14+F14-Source_Totals!Q14 -> 1324.1069 | H14: =Source_Totals!P14 -> 425.79744 | I14: =E14+F14-G14 -> -986.21551 | J14: =E14+F14-H14 -> -87.906047 | K14: =H14-G14 -> -898.30946 | L14: =G14-H14 -> 898.30946 | M14: =K14+L14 -> 0 | N14: =Source_Totals!M14-Source_Totals!O14-L14 -> 0
A15: =Source_Totals!A15 -> a0.20_C_15kWh | B15: =Source_Totals!B15 -> 0.2 | C15: =Source_Totals!C15 -> C | D15: =Source_Totals!D15 -> 15 | E15: =Source_Totals!N15-Source_Totals!O15 -> 163.4652 | F15: =Source_Totals!V15*(Source_Totals!H15+Source_Totals!I15) -> 240.04079 | G15: =E15+F15-Source_Totals!Q15 -> 1441.8254 | H15: =Source_Totals!P15 -> 459.32611 | I15: =E15+F15-G15 -> -1038.3194 | J15: =E15+F15-H15 -> -55.820122 | K15: =H15-G15 -> -982.4993 | L15: =G15-H15 -> 982.4993 | M15: =K15+L15 -> 0 | N15: =Source_Totals!M15-Source_Totals!O15-L15 -> 0
A16: =Source_Totals!A16 -> a0.20_C_20kWh | B16: =Source_Totals!B16 -> 0.2 | C16: =Source_Totals!C16 -> C | D16: =Source_Totals!D16 -> 20 | E16: =Source_Totals!N16-Source_Totals!O16 -> 172.23845 | F16: =Source_Totals!V16*(Source_Totals!H16+Source_Totals!I16) -> 284.82261 | G16: =E16+F16-Source_Totals!Q16 -> 1525.4399 | H16: =Source_Totals!P16 -> 492.18794 | I16: =E16+F16-G16 -> -1068.3788 | J16: =E16+F16-H16 -> -35.126873 | K16: =H16-G16 -> -1033.252 | L16: =G16-H16 -> 1033.252 | M16: =K16+L16 -> 0 | N16: =Source_Totals!M16-Source_Totals!O16-L16 -> 0
A17: =Source_Totals!A17 -> a0.20_C_30kWh | B17: =Source_Totals!B17 -> 0.2 | C17: =Source_Totals!C17 -> C | D17: =Source_Totals!D17 -> 30 | E17: =Source_Totals!N17-Source_Totals!O17 -> 181.77784 | F17: =Source_Totals!V17*(Source_Totals!H17+Source_Totals!I17) -> 316.6241 | G17: =E17+F17-Source_Totals!Q17 -> 1586.4013 | H17: =Source_Totals!P17 -> 517.37345 | I17: =E17+F17-G17 -> -1087.9994 | J17: =E17+F17-H17 -> -18.971509 | K17: =H17-G17 -> -1069.0279 | L17: =G17-H17 -> 1069.0279 | M17: =K17+L17 -> 0 | N17: =Source_Totals!M17-Source_Totals!O17-L17 -> 0
... A41: =Source_Totals!A41 -> a0.30_C_30kWh | B41: =Source_Totals!B41 -> 0.3 | C41: =Source_Totals!C41 -> C | D41: =Source_Totals!D41 -> 30 | E41: =Source_Totals!N41-Source_Totals!O41 -> 181.77784 | F41: =Source_Totals!V41*(Source_Totals!H41+Source_Totals!I41) -> 316.6241 | G41: =E41+F41-Source_Totals!Q41 -> 1586.4013 | H41: =Source_Totals!P41 -> 517.37345 | I41: =E41+F41-G41 -> -1087.9994 | J41: =E41+F41-H41 -> -18.971509 | K41: =H41-G41 -> -1069.0279 | L41: =G41-H41 -> 1069.0279 | M41: =K41+L41 -> 0 | N41: =Source_Totals!M41-Source_Totals!O41-L41 -> 0

Sheet Baseline_025
A1: BASELINE | α = 0.25
A2: Twelve configurations from the new calibration. Values link to the 36-case sheets; not to pre-review outputs.
A5: Strategy | B5: Battery (kWh) | C5: Grid→load (kWh) | D5: All imports (kWh) | E5: Exports / injection (kWh) | F5: Spot receipts (€) | G5: P2P receipts (€) | H5: Seller receipts change (€) | I5: Direct PV / generation (%) | J5: P2P net cost (€)
A6: =Energy_36!C18 -> A | B6: =Energy_36!D18 -> 10 | C6: =Energy_36!H18 -> 1550.7249 | D6: =Energy_36!I18 -> 1550.7249 | E6: =Energy_36!K18 -> 12641.75 | F6: =Cashflows_36!G18 -> 1050.2667 | G6: =Cashflows_36!H18 -> 480.81207 | H6: =Cashflows_36!K18 -> -569.45468 | I6: =Energy_36!P18 -> 0.12088689 | J6: =Cashflows_36!J18 -> -256.65326
A7: =Energy_36!C19 -> A | B7: =Energy_36!D19 -> 15 | C7: =Energy_36!H19 -> 1546.5913 | D7: =Energy_36!I19 -> 1546.5913 | E7: =Energy_36!K19 -> 12635.472 | F7: =Cashflows_36!G19 -> 1049.6935 | G7: =Cashflows_36!H19 -> 480.26964 | H7: =Cashflows_36!K19 -> -569.42381 | I7: =Energy_36!P19 -> 0.12088689 | J7: =Cashflows_36!J19 -> -256.43135
A8: =Energy_36!C20 -> A | B8: =Energy_36!D20 -> 20 | C8: =Energy_36!H20 -> 1546.3494 | D8: =Energy_36!I20 -> 1546.3494 | E8: =Energy_36!K20 -> 12633.787 | F8: =Cashflows_36!G20 -> 1049.5973 | G8: =Cashflows_36!H20 -> 480.18561 | H8: =Cashflows_36!K20 -> -569.4117 | I8: =Energy_36!P20 -> 0.12088689 | J8: =Cashflows_36!J20 -> -256.32372
A9: =Energy_36!C21 -> A | B9: =Energy_36!D21 -> 30 | C9: =Energy_36!H21 -> 1546.3494 | D9: =Energy_36!I21 -> 1546.3494 | E9: =Energy_36!K21 -> 12630.989 | F9: =Cashflows_36!G21 -> 1049.4549 | G9: =Cashflows_36!H21 -> 480.08142 | H9: =Cashflows_36!K21 -> -569.37352 | I9: =Energy_36!P21 -> 0.12088689 | J9: =Cashflows_36!J21 -> -256.13558
A10: =Energy_36!C22 -> B | B10: =Energy_36!D22 -> 10 | C10: =Energy_36!H22 -> 2002.7729 | D10: =Energy_36!I22 -> 3229.4218 | E10: =Energy_36!K22 -> 14031.312 | F10: =Cashflows_36!G22 -> 1396.345 | G10: =Cashflows_36!H22 -> 762.17559 | H10: =Cashflows_36!K22 -> -634.16937 | I10: =Energy_36!P22 -> 0.12088689 | J10: =Cashflows_36!J22 -> -273.65248
A11: =Energy_36!C23 -> B | B11: =Energy_36!D23 -> 15 | C11: =Energy_36!H23 -> 1928.935 | D11: =Energy_36!I23 -> 3358.6865 | E11: =Energy_36!K23 -> 14027.464 | F11: =Cashflows_36!G23 -> 1486.4026 | G11: =Cashflows_36!H23 -> 767.4608 | H11: =Cashflows_36!K23 -> -718.94181 | I11: =Energy_36!P23 -> 0.12088689 | J11: =Cashflows_36!J23 -> -223.98104
A12: =Energy_36!C24 -> B | B12: =Energy_36!D24 -> 20 | C12: =Energy_36!H24 -> 1852.1606 | D12: =Energy_36!I24 -> 3411.0092 | E12: =Energy_36!K24 -> 13989.167 | F12: =Cashflows_36!G24 -> 1535.1353 | G12: =Cashflows_36!H24 -> 786.85479 | H12: =Cashflows_36!K24 -> -748.28053 | I12: =Energy_36!P24 -> 0.12088689 | J12: =Cashflows_36!J24 -> -207.58963
A13: =Energy_36!C25 -> B | B13: =Energy_36!D25 -> 30 | C13: =Energy_36!H25 -> 1815.8275 | D13: =Energy_36!I25 -> 3510.5929 | E13: =Energy_36!K25 -> 14005.915 | F13: =Cashflows_36!G25 -> 1577.6786 | G13: =Cashflows_36!H25 -> 805.29139 | H13: =Cashflows_36!K25 -> -772.38718 | I13: =Energy_36!P25 -> 0.12088689 | J13: =Cashflows_36!J25 -> -185.1514
A14: =Energy_36!C26 -> C | B14: =Energy_36!D26 -> 10 | C14: =Energy_36!H26 -> 1401.7179 | D14: =Energy_36!I26 -> 1722.3726 | E14: =Energy_36!K26 -> 12475.726 | F14: =Cashflows_36!G26 -> 1324.1069 | G14: =Cashflows_36!H26 -> 425.79744 | H14: =Cashflows_36!K26 -> -898.30946 | I14: =Energy_36!P26 -> 0.14242623 | J14: =Cashflows_36!J26 -> -87.906047
A15: =Energy_36!C27 -> C | B15: =Energy_36!D27 -> 15 | C15: =Energy_36!H27 -> 1362.9558 | D15: =Energy_36!I27 -> 1938.7559 | E15: =Energy_36!K27 -> 12513.658 | F15: =Cashflows_36!G27 -> 1441.8254 | G15: =Cashflows_36!H27 -> 459.32611 | H15: =Cashflows_36!K27 -> -982.4993 | I15: =Energy_36!P27 -> 0.14242623 | J15: =Cashflows_36!J27 -> -55.820122
A16: =Energy_36!C28 -> C | B16: =Energy_36!D28 -> 20 | C16: =Energy_36!H28 -> 1347.5186 | D16: =Energy_36!I28 -> 2328.4494 | E16: =Energy_36!K28 -> 12778.659 | F16: =Cashflows_36!G28 -> 1525.4399 | G16: =Cashflows_36!H28 -> 492.18794 | H16: =Cashflows_36!K28 -> -1033.252 | I16: =Energy_36!P28 -> 0.14242623 | J16: =Cashflows_36!J28 -> -35.126873
A17: =Energy_36!C29 -> C | B17: =Energy_36!D29 -> 30 | C17: =Energy_36!H29 -> 1343.0334 | D17: =Energy_36!I29 -> 2787.6931 | E17: =Energy_36!K29 -> 13148.397 | F17: =Cashflows_36!G29 -> 1586.4013 | G17: =Cashflows_36!H29 -> 517.37345 | H17: =Cashflows_36!K29 -> -1069.0279 | I17: =Energy_36!P29 -> 0.14242623 | J17: =Cashflows_36!J29 -> -18.971509

Sheet Alpha_Ranges
A1: SENSITIVITY | MATCHED STRATEGY AND CAPACITY
A2: Only α varies independently; omega is recalibrated from the same daily mean price and base load. Min/max are deterministic scenario ranges, not confidence intervals.
A5: Strategy | B5: Battery (kWh) | C5: Exports α=.20 (kWh) | D5: Exports α=.25 (kWh) | E5: Exports α=.30 (kWh) | F5: Exports change .20→.30 (%) | G5: P2P receipts α=.20 (€) | H5: P2P receipts α=.25 (€) | I5: P2P receipts α=.30 (€) | J5: Min seller receipt change (€) | K5: Max seller receipt change (€) | L5: Min direct PV share (%) | M5: Max direct PV share (%)
A6: =Energy_36!C18 -> A | B6: =Energy_36!D18 -> 10 | C6: =Energy_36!K6 -> 12644.42 | D6: =Energy_36!K18 -> 12641.75 | E6: =Energy_36!K30 -> 12640.484 | F6: =E6/C6-1 -> -0.0003112991 | G6: =Cashflows_36!H6 -> 478.32015 | H6: =Cashflows_36!H18 -> 480.81207 | I6: =Cashflows_36!H30 -> 483.05529 | J6: =MIN(Cashflows_36!K6,Cashflows_36!K18,Cashflows_36!K30) -> -581.93765 | K6: =MAX(Cashflows_36!K6,Cashflows_36!K18,Cashflows_36!K30) -> -559.82452 | L6: =MIN(Energy_36!P6,Energy_36!P18,Energy_36!P30) -> 0.11615273 | M6: =MAX(Energy_36!P6,Energy_36!P18,Energy_36!P30) -> 0.12423391
A7: =Energy_36!C19 -> A | B7: =Energy_36!D19 -> 15 | C7: =Energy_36!K7 -> 12638.142 | D7: =Energy_36!K19 -> 12635.472 | E7: =Energy_36!K31 -> 12634.289 | F7: =E7/C7-1 -> -0.00030490022 | G7: =Cashflows_36!H7 -> 477.77843 | H7: =Cashflows_36!H19 -> 480.26964 | I7: =Cashflows_36!H31 -> 482.52273 | J7: =MIN(Cashflows_36!K7,Cashflows_36!K19,Cashflows_36!K31) -> -581.907 | K7: =MAX(Cashflows_36!K7,Cashflows_36!K19,Cashflows_36!K31) -> -559.79136 | L7: =MIN(Energy_36!P7,Energy_36!P19,Energy_36!P31) -> 0.11615273 | M7: =MAX(Energy_36!P7,Energy_36!P19,Energy_36!P31) -> 0.12423391
A8: =Energy_36!C20 -> A | B8: =Energy_36!D20 -> 20 | C8: =Energy_36!K8 -> 12635.905 | D8: =Energy_36!K20 -> 12633.787 | E8: =Energy_36!K32 -> 12632.889 | F8: =E8/C8-1 -> -0.00023863333 | G8: =Cashflows_36!H8 -> 477.63896 | H8: =Cashflows_36!H20 -> 480.18561 | I8: =Cashflows_36!H32 -> 482.46808 | J8: =MIN(Cashflows_36!K8,Cashflows_36!K20,Cashflows_36!K32) -> -581.89534 | K8: =MAX(Cashflows_36!K8,Cashflows_36!K20,Cashflows_36!K32) -> -559.77823 | L8: =MIN(Energy_36!P8,Energy_36!P20,Energy_36!P32) -> 0.11615273 | M8: =MAX(Energy_36!P8,Energy_36!P20,Energy_36!P32) -> 0.12423391
A9: =Energy_36!C21 -> A | B9: =Energy_36!D21 -> 30 | C9: =Energy_36!K9 -> 12633.106 | D9: =Energy_36!K21 -> 12630.989 | E9: =Energy_36!K33 -> 12630.091 | F9: =E9/C9-1 -> -0.00023868704 | G9: =Cashflows_36!H9 -> 477.5441 | H9: =Cashflows_36!H21 -> 480.08142 | I9: =Cashflows_36!H33 -> 482.35711 | J9: =MIN(Cashflows_36!K9,Cashflows_36!K21,Cashflows_36!K33) -> -581.84796 | K9: =MAX(Cashflows_36!K9,Cashflows_36!K21,Cashflows_36!K33) -> -559.74669 | L9: =MIN(Energy_36!P9,Energy_36!P21,Energy_36!P33) -> 0.11615273 | M9: =MAX(Energy_36!P9,Energy_36!P21,Energy_36!P33) -> 0.12423391
A10: =Energy_36!C22 -> B | B10: =Energy_36!D22 -> 10 | C10: =Energy_36!K10 -> 14058.374 | D10: =Energy_36!K22 -> 14031.312 | E10: =Energy_36!K34 -> 14014.408 | F10: =E10/C10-1 -> -0.0031273666 | G10: =Cashflows_36!H10 -> 765.97812 | H10: =Cashflows_36!H22 -> 762.17559 | I10: =Cashflows_36!H34 -> 759.72618 | J10: =MIN(Cashflows_36!K10,Cashflows_36!K22,Cashflows_36!K34) -> -634.50198 | K10: =MAX(Cashflows_36!K10,Cashflows_36!K22,Cashflows_36!K34) -> -634.08119 | L10: =MIN(Energy_36!P10,Energy_36!P22,Energy_36!P34) -> 0.11615273 | M10: =MAX(Energy_36!P10,Energy_36!P22,Energy_36!P34) -> 0.12423391
A11: =Energy_36!C23 -> B | B11: =Energy_36!D23 -> 15 | C11: =Energy_36!K11 -> 14048.562 | D11: =Energy_36!K23 -> 14027.464 | E11: =Energy_36!K35 -> 14013.55 | F11: =E11/C11-1 -> -0.0024922363 | G11: =Cashflows_36!H11 -> 770.63407 | H11: =Cashflows_36!H23 -> 767.4608 | I11: =Cashflows_36!H35 -> 765.37279 | J11: =MIN(Cashflows_36!K11,Cashflows_36!K23,Cashflows_36!K35) -> -719.04097 | K11: =MAX(Cashflows_36!K11,Cashflows_36!K23,Cashflows_36!K35) -> -718.79197 | L11: =MIN(Energy_36!P11,Energy_36!P23,Energy_36!P35) -> 0.11615273 | M11: =MAX(Energy_36!P11,Energy_36!P23,Energy_36!P35) -> 0.12423391
A12: =Energy_36!C24 -> B | B12: =Energy_36!D24 -> 20 | C12: =Energy_36!K12 -> 14009.28 | D12: =Energy_36!K24 -> 13989.167 | E12: =Energy_36!K36 -> 13975.883 | F12: =E12/C12-1 -> -0.002383924 | G12: =Cashflows_36!H12 -> 789.88404 | H12: =Cashflows_36!H24 -> 786.85479 | I12: =Cashflows_36!H36 -> 784.86006 | J12: =MIN(Cashflows_36!K12,Cashflows_36!K24,Cashflows_36!K36) -> -748.38473 | K12: =MAX(Cashflows_36!K12,Cashflows_36!K24,Cashflows_36!K36) -> -748.11301 | L12: =MIN(Energy_36!P12,Energy_36!P24,Energy_36!P36) -> 0.11615273 | M12: =MAX(Energy_36!P12,Energy_36!P24,Energy_36!P36) -> 0.12423391
A13: =Energy_36!C25 -> B | B13: =Energy_36!D25 -> 30 | C13: =Energy_36!K13 -> 14026.101 | D13: =Energy_36!K25 -> 14005.915 | E13: =Energy_36!K37 -> 13992.569 | F13: =E13/C13-1 -> -0.0023906886 | G13: =Cashflows_36!H13 -> 808.26956 | H13: =Cashflows_36!H25 -> 805.29139 | I13: =Cashflows_36!H37 -> 803.33387 | J13: =MIN(Cashflows_36!K13,Cashflows_36!K25,Cashflows_36!K37) -> -772.45122 | K13: =MAX(Cashflows_36!K13,Cashflows_36!K25,Cashflows_36!K37) -> -772.2664 | L13: =MIN(Energy_36!P13,Energy_36!P25,Energy_36!P37) -> 0.11615273 | M13: =MAX(Energy_36!P13,Energy_36!P25,Energy_36!P37) -> 0.12423391
A14: =Energy_36!C26 -> C | B14: =Energy_36!D26 -> 10 | C14: =Energy_36!K14 -> 12475.726 | D14: =Energy_36!K26 -> 12475.726 | E14: =Energy_36!K38 -> 12475.726 | F14: =E14/C14-1 -> 0 | G14: =Cashflows_36!H14 -> 425.79744 | H14: =Cashflows_36!H26 -> 425.79744 | I14: =Cashflows_36!H38 -> 425.79744 | J14: =MIN(Cashflows_36!K14,Cashflows_36!K26,Cashflows_36!K38) -> -898.30946 | K14: =MAX(Cashflows_36!K14,Cashflows_36!K26,Cashflows_36!K38) -> -898.30946 | L14: =MIN(Energy_36!P14,Energy_36!P26,Energy_36!P38) -> 0.14242623 | M14: =MAX(Energy_36!P14,Energy_36!P26,Energy_36!P38) -> 0.14242623
A15: =Energy_36!C27 -> C | B15: =Energy_36!D27 -> 15 | C15: =Energy_36!K15 -> 12513.658 | D15: =Energy_36!K27 -> 12513.658 | E15: =Energy_36!K39 -> 12513.658 | F15: =E15/C15-1 -> 0 | G15: =Cashflows_36!H15 -> 459.32611 | H15: =Cashflows_36!H27 -> 459.32611 | I15: =Cashflows_36!H39 -> 459.32611 | J15: =MIN(Cashflows_36!K15,Cashflows_36!K27,Cashflows_36!K39) -> -982.4993 | K15: =MAX(Cashflows_36!K15,Cashflows_36!K27,Cashflows_36!K39) -> -982.4993 | L15: =MIN(Energy_36!P15,Energy_36!P27,Energy_36!P39) -> 0.14242623 | M15: =MAX(Energy_36!P15,Energy_36!P27,Energy_36!P39) -> 0.14242623
A16: =Energy_36!C28 -> C | B16: =Energy_36!D28 -> 20 | C16: =Energy_36!K16 -> 12778.659 | D16: =Energy_36!K28 -> 12778.659 | E16: =Energy_36!K40 -> 12778.659 | F16: =E16/C16-1 -> 0 | G16: =Cashflows_36!H16 -> 492.18794 | H16: =Cashflows_36!H28 -> 492.18794 | I16: =Cashflows_36!H40 -> 492.18794 | J16: =MIN(Cashflows_36!K16,Cashflows_36!K28,Cashflows_36!K40) -> -1033.252 | K16: =MAX(Cashflows_36!K16,Cashflows_36!K28,Cashflows_36!K40) -> -1033.252 | L16: =MIN(Energy_36!P16,Energy_36!P28,Energy_36!P40) -> 0.14242623 | M16: =MAX(Energy_36!P16,Energy_36!P28,Energy_36!P40) -> 0.14242623
A17: =Energy_36!C29 -> C | B17: =Energy_36!D29 -> 30 | C17: =Energy_36!K17 -> 13148.397 | D17: =Energy_36!K29 -> 13148.397 | E17: =Energy_36!K41 -> 13148.397 | F17: =E17/C17-1 -> 0 | G17: =Cashflows_36!H17 -> 517.37345 | H17: =Cashflows_36!H29 -> 517.37345 | I17: =Cashflows_36!H41 -> 517.37345 | J17: =MIN(Cashflows_36!K17,Cashflows_36!K29,Cashflows_36!K41) -> -1069.0279 | K17: =MAX(Cashflows_36!K17,Cashflows_36!K29,Cashflows_36!K41) -> -1069.0279 | L17: =MIN(Energy_36!P17,Energy_36!P29,Energy_36!P41) -> 0.14242623 | M17: =MAX(Energy_36!P17,Energy_36!P29,Energy_36!P41) -> 0.14242623

Sheet Capacity_Check
A1: CAPACITY | ENDPOINT COMPARISON 10 → 30 kWh
A2: Endpoint comparison only; it does not imply monotonicity at 15 and 20 kWh. Grid-to-load and total imports are different measures. Energy units: kWh.
A5: Strategy | B5: α (€/kWh²) | C5: Exports 10 kWh | D5: Exports 30 kWh | E5: Exports change (kWh) | F5: Exports change (%) | G5: Grid→load 10 kWh | H5: Grid→load 30 kWh | I5: All imports 10 kWh | J5: All imports 30 kWh | K5: All imports change (kWh)
A6: =Energy_36!C6 -> A | B6: =Energy_36!B6 -> 0.2 | C6: =Energy_36!K6 -> 12644.42 | D6: =Energy_36!K9 -> 12633.106 | E6: =D6-C6 -> -11.314055 | F6: =D6/C6-1 -> -0.00089478635 | G6: =Energy_36!H6 -> 1564.1112 | H6: =Energy_36!H9 -> 1559.2673 | I6: =Energy_36!I6 -> 1564.1112 | J6: =Energy_36!I9 -> 1559.2673 | K6: =J6-I6 -> -4.8439731
A7: =Energy_36!C10 -> B | B7: =Energy_36!B10 -> 0.2 | C7: =Energy_36!K10 -> 14058.374 | D7: =Energy_36!K13 -> 14026.101 | E7: =D7-C7 -> -32.273495 | F7: =D7/C7-1 -> -0.0022956776 | G7: =Energy_36!H10 -> 2032.1835 | H7: =Energy_36!H13 -> 1838.4999 | I7: =Energy_36!I10 -> 3256.4872 | J7: =Energy_36!I13 -> 3530.7852 | K7: =J7-I7 -> 274.29793
A8: =Energy_36!C14 -> C | B8: =Energy_36!B14 -> 0.2 | C8: =Energy_36!K14 -> 12475.726 | D8: =Energy_36!K17 -> 13148.397 | E8: =D8-C8 -> 672.67045 | F8: =D8/C8-1 -> 0.05391834 | G8: =Energy_36!H14 -> 1401.7179 | H8: =Energy_36!H17 -> 1343.0334 | I8: =Energy_36!I14 -> 1722.3726 | J8: =Energy_36!I17 -> 2787.6931 | K8: =J8-I8 -> 1065.3205
A9: =Energy_36!C18 -> A | B9: =Energy_36!B18 -> 0.25 | C9: =Energy_36!K18 -> 12641.75 | D9: =Energy_36!K21 -> 12630.989 | E9: =D9-C9 -> -10.761557 | F9: =D9/C9-1 -> -0.00085127109 | G9: =Energy_36!H18 -> 1550.7249 | H9: =Energy_36!H21 -> 1546.3494 | I9: =Energy_36!I18 -> 1550.7249 | J9: =Energy_36!I21 -> 1546.3494 | K9: =J9-I9 -> -4.3754866
A10: =Energy_36!C22 -> B | B10: =Energy_36!B22 -> 0.25 | C10: =Energy_36!K22 -> 14031.312 | D10: =Energy_36!K25 -> 14005.915 | E10: =D10-C10 -> -25.397328 | F10: =D10/C10-1 -> -0.0018100466 | G10: =Energy_36!H22 -> 2002.7729 | H10: =Energy_36!H25 -> 1815.8275 | I10: =Energy_36!I22 -> 3229.4218 | J10: =Energy_36!I25 -> 3510.5929 | K10: =J10-I10 -> 281.17106
A11: =Energy_36!C26 -> C | B11: =Energy_36!B26 -> 0.25 | C11: =Energy_36!K26 -> 12475.726 | D11: =Energy_36!K29 -> 13148.397 | E11: =D11-C11 -> 672.67045 | F11: =D11/C11-1 -> 0.05391834 | G11: =Energy_36!H26 -> 1401.7179 | H11: =Energy_36!H29 -> 1343.0334 | I11: =Energy_36!I26 -> 1722.3726 | J11: =Energy_36!I29 -> 2787.6931 | K11: =J11-I11 -> 1065.3205
A12: =Energy_36!C30 -> A | B12: =Energy_36!B30 -> 0.3 | C12: =Energy_36!K30 -> 12640.484 | D12: =Energy_36!K33 -> 12630.091 | E12: =D12-C12 -> -10.393217 | F12: =D12/C12-1 -> -0.00082221666 | G12: =Energy_36!H30 -> 1541.7825 | H12: =Energy_36!H33 -> 1537.7193 | I12: =Energy_36!I30 -> 1541.7825 | J12: =Energy_36!I33 -> 1537.7193 | K12: =J12-I12 -> -4.0631972
A13: =Energy_36!C34 -> B | B13: =Energy_36!B34 -> 0.3 | C13: =Energy_36!K34 -> 14014.408 | D13: =Energy_36!K37 -> 13992.569 | E13: =D13-C13 -> -21.839844 | F13: =D13/C13-1 -> -0.001558385 | G13: =Energy_36!H34 -> 1984.406 | H13: =Energy_36!H37 -> 1800.8968 | I13: =Energy_36!I34 -> 3212.5162 | J13: =Energy_36!I37 -> 3497.2427 | K13: =J13-I13 -> 284.72652
A14: =Energy_36!C38 -> C | B14: =Energy_36!B38 -> 0.3 | C14: =Energy_36!K38 -> 12475.726 | D14: =Energy_36!K41 -> 13148.397 | E14: =D14-C14 -> 672.67045 | F14: =D14/C14-1 -> 0.05391834 | G14: =Energy_36!H38 -> 1401.7179 | H14: =Energy_36!H41 -> 1343.0334 | I14: =Energy_36!I38 -> 1722.3726 | J14: =Energy_36!I41 -> 2787.6931 | K14: =J14-I14 -> 1065.3205
